{"bookId":43,"locale":"en","duration":28,"keyTakeaways":["Art demands sacrifice—Strickland abandons everything for his vision","Society's judgment of genius is often wrong","Beauty can emerge from ugliness, creation from destruction","The artist's inner compulsion transcends morality and convention","Telling someone's story means interpreting their mystery"],"summary_short":"Inspired by Gauguin's life, Maugham tells of Charles Strickland, a London stockbroker who abandons family and career to paint in Paris and Tahiti. Through a narrator who knew him, we explore the mystery of artistic genius and its human costs.","summary_medium":"<h2>Why This Book Matters</h2><p>The Moon and Sixpence asks uncomfortable questions about genius and morality. Strickland is cruel, selfish, and irresponsible—yet creates beauty that outlasts his cruelty. Must we excuse artists because of their art?</p><h2>The Transformation</h2><p>Strickland was a respectable broker. At 40, something breaks: he must paint. He abandons wife, children, comfort—everything that made him ordinary.</p><h2>The Art</h2><p>In Tahiti, sick and isolated, Strickland creates his masterpiece—then orders it burned after his death. The narrator glimpses it once and is forever changed.</p>"}
